snakemake_storage_plugin_webdav/__init__.py
snakemake_storage_plugin_webdav-0.1.2.dist-info/LICENSE
snakemake_storage_plugin_webdav-0.1.2.dist-info/METADATA
snakemake_storage_plugin_webdav-0.1.2.dist-info/WHEEL
snakemake_storage_plugin_webdav-0.1.2.dist-info/RECORD
